setup.py
pyTextUtil.egg-info/.DS_Store
pyTextUtil.egg-info/PKG-INFO
pyTextUtil.egg-info/SOURCES.txt
pyTextUtil.egg-info/dependency_links.txt
pyTextUtil.egg-info/entry_points.txt
pyTextUtil.egg-info/top_level.txt
src/__init__.py
src/command_line.py
src/delete.py
src/search.py
src/smart_open.py
src/textUtil.py
src/trim.py