Metadata-Version: 1.1
Name: pyTextUtil
Version: 0.0.6
Summary: simple text utils for python
Home-page: https://github.com/papower1/pyTextUtil
Author: papower
Author-email: papower2@gmail.com
License: Apache License 2.0
Keywords: textutil,textUtil,pytextutil,pyTextUtil
Platform: UNKNOWN
Classifier: Development Status :: 3 - Alpha
Classifier: Intended Audience :: Developers
Classifier: Programming Language :: Python
Classifier: Programming Language :: Python :: 2
Classifier: Operating System :: OS Independent
